.DS_Store
.gitignore
MANIFEST.in
README.md
bin.py
demo.ppts
setup.py
ppts.egg-info/PKG-INFO
ppts.egg-info/SOURCES.txt
ppts.egg-info/dependency_links.txt
ppts.egg-info/entry_points.txt
ppts.egg-info/top_level.txt
web/global.css
web/index.html
web/index.js
web/index.vue
web/package.json
web/slide.vue