Metadata-Version: 1.0
Name: ppts
Version: 1.0.26
Summary: ppt with web
Home-page: UNKNOWN
Author: simdd
Author-email: dev.simdd@gmail.com
License: UNKNOWN
Platform: UNKNOWN
